{
  "id": "doc_f8fc0670d07d",
  "docType": "document",
  "name": "策划方案",
  "contentFormat": "tiptap-json",
  "content": {
    "type": "doc",
    "content": [
      {
        "type": "heading",
        "attrs": {
          "textAlign": null,
          "level": 1
        },
        "content": [
          {
            "type": "text",
            "text": "一院·一程·一归家——岚图泰山X8「庭院级大五座SUV」新品城市级发布活动策划方案"
          }
        ]
      },
      {
        "type": "paragraph",
        "attrs": {
          "textAlign": null
        },
        "content": [
          {
            "type": "text",
            "text": "---"
          }
        ]
      },
      {
        "type": "heading",
        "attrs": {
          "textAlign": null,
          "level": 2
        },
        "content": [
          {
            "type": "text",
            "text": "第一章：策略总纲"
          }
        ]
      },
      {
        "type": "heading",
        "attrs": {
          "textAlign": null,
          "level": 3
        },
        "content": [
          {
            "type": "text",
            "text": "核心命题"
          }
        ]
      },
      {
        "type": "paragraph",
        "attrs": {
          "textAlign": null
        },
        "content": [
          {
            "type": "text",
            "text": "岚图泰山X8的市场竞争本质上是「情感定义权」之争。当前25-45万新能源SUV市场产品力趋同，问界M6以「弱化情绪营销、聚焦核心价值」策略赢得10万预售订单，验证了「功能价值直击人心」的有效性。但岚图泰山X8的独特机遇在于：竞品卖的是「产品参数」，我们要卖的是「生活方式」——把「庭院级」从一句定位语，变成一座可走进、可感受、可带回家的真实空间。"
          }
        ]
      },
      {
        "type": "heading",
        "attrs": {
          "textAlign": null,
          "level": 3
        },
        "content": [
          {
            "type": "text",
            "text": "战略判断"
          }
        ]
      },
      {
        "type": "paragraph",
        "attrs": {
          "textAlign": null
        },
        "content": [
          {
            "type": "text",
            "text": "我们判断：「庭院」是岚图泰山X8最强大的未开发资产。这两个字承载了中国家庭用户对「家」的全部想象——围合感、安全感、层次感、归属感。6.1平米座舱不是车内空间数字，它是「庭院级」的情感容器。活动现场的任务不是展示参数，而是让用户亲身进入这个容器，在移步换景中完成从「参观者」到「归家人」的身份转换。"
          }
        ]
      },
      {
        "type": "heading",
        "attrs": {
          "textAlign": null,
          "level": 3
        },
        "content": [
          {
            "type": "text",
            "text": "创意核心"
          }
        ]
      },
      {
        "type": "paragraph",
        "attrs": {
          "textAlign": null
        },
        "content": [
          {
            "type": "text",
            "text": "「一院·一程·一归家」——以一座微型中式庭院承载新车亮相，将5200mm的「大」翻译为「庭院的尺度感」，将六款车色翻译为六种「归家的情绪时刻」，将华为双联屏翻译为「归家的入口」。活动全程不设传统展车台，车型即是空间，空间即是故事，用户踏入庭院的那一刻，即是「回家」的开始。"
          }
        ]
      },
      {
        "type": "heading",
        "attrs": {
          "textAlign": null,
          "level": 3
        },
        "content": [
          {
            "type": "text",
            "text": "差异化定位"
          }
        ]
      },
      {
        "type": "paragraph",
        "attrs": {
          "textAlign": null
        },
        "content": [
          {
            "type": "text",
            "text": "维度岚图泰山X8主流竞品（问界M6/小鹏G7）传播语言庭院级、归家、幸福容器智能驾驶、续航、参数体验设计场景替代情绪，空间替代参数参数演示、对比讲解情感锚点「出行是离家的路，也是回家的路」科技感、未来感、性能用户角色归家人潜在车主"
          }
        ]
      },
      {
        "type": "paragraph",
        "attrs": {
          "textAlign": null
        },
        "content": [
          {
            "type": "text",
            "text": "---"
          }
        ]
      },
      {
        "type": "heading",
        "attrs": {
          "textAlign": null,
          "level": 2
        },
        "content": [
          {
            "type": "text",
            "text": "第二章：五大亮点方向"
          }
        ]
      },
      {
        "type": "heading",
        "attrs": {
          "textAlign": null,
          "level": 3
        },
        "content": [
          {
            "type": "text",
            "text": "亮点一：庭院叙事场"
          }
        ]
      },
      {
        "type": "paragraph",
        "attrs": {
          "textAlign": null
        },
        "content": [
          {
            "type": "text",
            "marks": [
              {
                "type": "bold"
              }
            ],
            "text": "设计思路："
          },
          {
            "type": "text",
            "text": " 活动主视觉与动线不设传统展车台，而是以一座微型中式庭院承载新车亮相。整体空间采用「廊道→前院→中庭→后院」四进布局，每一进对应产品一个核心卖点：廊道呈现尺寸体量（5200mm），前院呈现空间尺度（6.1平米），中庭呈现座椅模式（三种场景），后院呈现智能交互（华为双联屏）。用户进入庭院的过程即是阅读产品说明书的过程，但全程无文字、无讲解、无说教，只有「移步换景」的诗意体验。"
          }
        ]
      },
      {
        "type": "paragraph",
        "attrs": {
          "textAlign": null
        },
        "content": [
          {
            "type": "text",
            "marks": [
              {
                "type": "bold"
              }
            ],
            "text": "关键设计要素："
          },
          {
            "type": "text",
            "text": " 矮墙分隔空间层次，框景借景形成视觉焦点，中式灯笼与竹影营造围合感，地面水墨投影暗示六色车色路径。六款车色「玄英黑·杜若白·宸星灰·星光银·碧玺红·远山蓝」作为空间节点色彩引导，玄英黑对应深夜寂静的夜空，碧玺红对应归家时客厅的暖光，远山蓝对应山巅眺望的天际线——每个颜色都是一个「归家的情绪时刻」，用户可在此打卡留影，形成社交传播素材。"
          }
        ]
      },
      {
        "type": "paragraph",
        "attrs": {
          "textAlign": null
        },
        "content": [
          {
            "type": "text",
            "marks": [
              {
                "type": "bold"
              }
            ],
            "text": "空间节奏控制："
          },
          {
            "type": "text",
            "text": " 庭院动线全程约45分钟，设置5处驻足节点（入口廊道、前院水景、中庭座椅剧场、后院双联屏体验区、车型揭幕区），每个节点停留8-10分钟，既保证体验完整性，又避免疲劳感。"
          }
        ]
      },
      {
        "type": "heading",
        "attrs": {
          "textAlign": null,
          "level": 3
        },
        "content": [
          {
            "type": "text",
            "text": "亮点二：场景一键剧场"
          }
        ]
      },
      {
        "type": "paragraph",
        "attrs": {
          "textAlign": null
        },
        "content": [
          {
            "type": "text",
            "marks": [
              {
                "type": "bold"
              }
            ],
            "text": "设计思路："
          },
          {
            "type": "text",
            "text": " 在固定点位设置总统大三座、豪华大四座、宽绰大五座三种座椅模式的一键切换演示。与传统静态展示不同，每次切换配合光影变化+音效变化+场景视频，对应一个真实生活场景：车内午休场景（职场精英午后休憩）、亲子露营场景（三代同堂户外周末）、全家出行场景（春节返乡长途旅行）。让产品功能自己讲故事，用户在「啊，原来可以这样用」的瞬间完成功能认知。"
          }
        ]
      },
      {
        "type": "paragraph",
        "attrs": {
          "textAlign": null
        },
        "content": [
          {
            "type": "text",
            "marks": [
              {
                "type": "bold"
              }
            ],
            "text": "技术实现："
          },
          {
            "type": "text",
            "text": " 座椅切换触发三屏联动——座椅机构物理移动（15秒）、顶部星空灯带变色（10秒）、前方的投影幕布播放对应场景视频（30秒）、背景音乐切换（全程），形成完整的「场景进入」体验。每组演示时长3分钟，循环播放，宾客可随时进入体验。"
          }
        ]
      },
      {
        "type": "paragraph",
        "attrs": {
          "textAlign": null
        },
        "content": [
          {
            "type": "text",
            "marks": [
              {
                "type": "bold"
              }
            ],
            "text": "场景内容设计："
          }
        ]
      },
      {
        "type": "bulletList",
        "content": [
          {
            "type": "listItem",
            "content": [
              {
                "type": "paragraph",
                "attrs": {
                  "textAlign": null
                },
                "content": [
                  {
                    "type": "text",
                    "marks": [
                      {
                        "type": "bold"
                      }
                    ],
                    "text": "总统大三座"
                  },
                  {
                    "type": "text",
                    "text": "：场景设定「停车场午休」，画面是午后的车内场景，窗外城市车流穿梭，车内零重力座椅完全展开，氛围音乐是白噪音+轻柔钢琴，用户可同步体验座椅的包裹感与按摩功能"
                  }
                ]
              }
            ]
          },
          {
            "type": "listItem",
            "content": [
              {
                "type": "paragraph",
                "attrs": {
                  "textAlign": null
                },
                "content": [
                  {
                    "type": "text",
                    "marks": [
                      {
                        "type": "bold"
                      }
                    ],
                    "text": "豪华大四座"
                  },
                  {
                    "type": "text",
                    "text": "：场景设定「周末露营」，画面是户外草坪、儿童在车内玩耍、成年人坐在放倒的前排座椅上看书，氛围音乐是风声+虫鸣+轻爵士，用户可体验后排空间的「庭院感」"
                  }
                ]
              }
            ]
          },
          {
            "type": "listItem",
            "content": [
              {
                "type": "paragraph",
                "attrs": {
                  "textAlign": null
                },
                "content": [
                  {
                    "type": "text",
                    "marks": [
                      {
                        "type": "bold"
                      }
                    ],
                    "text": "宽绰大五座"
                  },
                  {
                    "type": "text",
                    "text": "：场景设定「春节回家」，画面是高速服务区休息、一家五口在车内吃东西、后备箱塞满年货，氛围音乐是春节熟悉的乡村民谣，用户可同时体验后备箱的大容量"
                  }
                ]
              }
            ]
          }
        ]
      },
      {
        "type": "heading",
        "attrs": {
          "textAlign": null,
          "level": 3
        },
        "content": [
          {
            "type": "text",
            "text": "亮点三：家书开场"
          }
        ]
      },
      {
        "type": "paragraph",
        "attrs": {
          "textAlign": null
        },
        "content": [
          {
            "type": "text",
            "marks": [
              {
                "type": "bold"
              }
            ],
            "text": "设计思路："
          },
          {
            "type": "text",
            "text": " 发布会不以领导人致辞开场，而是以一封车主视角的「给家的信」视频或音频作为首位呈现。视频内容由真实岚图车主出镜拍摄（非演员），讲述「我与家的故事」——可能是职场精英讲述每天开车回家路上的内心独白，可能是新手父母讲述第一次带新生儿出门的紧张与幸福，可能是中年子女讲述周末带父母看病的复杂情绪。视频结尾引入「出行是离家的路，也是回家的路」情感主轴，将产品发布锚定为「幸福的容器」而非「技术的载体」。"
          }
        ]
      },
      {
        "type": "paragraph",
        "attrs": {
          "textAlign": null
        },
        "content": [
          {
            "type": "text",
            "marks": [
              {
                "type": "bold"
              }
            ],
            "text": "执行细节："
          },
          {
            "type": "text",
            "text": " 视频时长3分钟，选用25-35岁真实车主出演（非职业演员），在真实场景中拍摄（车内、家庭、旅途），旁白文案坚持「不说产品、只说情感」，结尾一句：「我需要的不是一辆车，是一个可以回家的理由。岚图泰山X8，庭院级大五座，让每一次出行，都是回家的路。」"
          }
        ]
      },
      {
        "type": "paragraph",
        "attrs": {
          "textAlign": null
        },
        "content": [
          {
            "type": "text",
            "marks": [
              {
                "type": "bold"
              }
            ],
            "text": "仪式衔接："
          },
          {
            "type": "text",
            "text": " 「家书」结束后，灯光渐亮，现场音乐转为温暖轻快的家庭氛围，主持人简短引出车型亮相环节，衔接自然流畅，不打断情感流。"
          }
        ]
      },
      {
        "type": "heading",
        "attrs": {
          "textAlign": null,
          "level": 3
        },
        "content": [
          {
            "type": "text",
            "text": "亮点四：六色归山"
          }
        ]
      },
      {
        "type": "paragraph",
        "attrs": {
          "textAlign": null
        },
        "content": [
          {
            "type": "text",
            "marks": [
              {
                "type": "bold"
              }
            ],
            "text": "设计思路："
          },
          {
            "type": "text",
            "text": " 将六款车色的文化灵感从「颜色名称」升维为「情感叙事」。每个颜色对应一种「归家的情绪时刻」，在庭院动线中设置六个独立打卡节点，用户进入节点后，手机扫描二维码可解锁一段30秒音频或一段15秒视频，内容是关于这个颜色所代表的情感时刻：比如「碧玺红」对应的场景是「推开家门，客厅的灯亮着，餐桌上还留着一盏小灯」，用户扫码后看到的是一个家庭日常的视频片段，背景音是「归家」的钢琴曲。"
          }
        ]
      },
      {
        "type": "paragraph",
        "attrs": {
          "textAlign": null
        },
        "content": [
          {
            "type": "text",
            "marks": [
              {
                "type": "bold"
              }
            ],
            "text": "空间呈现："
          },
          {
            "type": "text",
            "text": " 六个节点分散布置于庭院四进空间中，每个节点以该颜色为主视觉基调，配合中式花艺（呼应车色来源的植物意象——玄英黑对应夜空、杜若白对应古典香草、碧玺红对应宝石色泽、远山蓝对应天际线），形成「色彩即叙事」的沉浸式体验。"
          }
        ]
      },
      {
        "type": "paragraph",
        "attrs": {
          "textAlign": null
        },
        "content": [
          {
            "type": "text",
            "marks": [
              {
                "type": "bold"
              }
            ],
            "text": "传播设计："
          },
          {
            "type": "text",
            "text": " 每个节点设置「情绪时刻拍照点」，提供新中式风格道具（如竹编灯笼、油纸伞、折扇），用户拍照后自动触发社交分享引导（小红书/抖音/微信朋友圈），文案模板为：「#岚图泰山X8 #六色归山，在【碧玺红】的节点，我想起的是……」"
          }
        ]
      },
      {
        "type": "heading",
        "attrs": {
          "textAlign": null,
          "level": 3
        },
        "content": [
          {
            "type": "text",
            "text": "亮点五：华为双屏即剧场"
          }
        ]
      },
      {
        "type": "paragraph",
        "attrs": {
          "textAlign": null
        },
        "content": [
          {
            "type": "text",
            "marks": [
              {
                "type": "bold"
              }
            ],
            "text": "设计思路："
          },
          {
            "type": "text",
            "text": " 将华为双15.6英寸大双联屏作为现场核心交互界面，车机界面即是发布会内容界面。用户上车那一刻即为「开场」，打破台上台下边界——车内用户通过双联屏看到的，正是舞台主持人讲解的内容，实现「人在车中坐，局在屏上演」的双向互动。"
          }
        ]
      },
      {
        "type": "paragraph",
        "attrs": {
          "textAlign": null
        },
        "content": [
          {
            "type": "text",
            "marks": [
              {
                "type": "bold"
              }
            ],
            "text": "执行方式："
          },
          {
            "type": "text",
            "text": " 发布会设定「双主线」——主线一为舞台上的主持人串场，主线二为车内用户的双联屏同步内容。主持人讲解每个功能点时，车内用户可在双联屏上同步看到这个功能的使用演示、参数对比、场景视频。华为双联屏不再是「功能配置展示」，而是「活动内容界面」，车机的每一帧画面都经过精心设计，确保视觉呈现与舞台节奏完美同步。"
          }
        ]
      },
      {
        "type": "paragraph",
        "attrs": {
          "textAlign": null
        },
        "content": [
          {
            "type": "text",
            "marks": [
              {
                "type": "bold"
              }
            ],
            "text": "互动设计："
          },
          {
            "type": "text",
            "text": " 在「场景一键剧场」环节，车内用户可在双联屏上主动触发三种座椅模式的切换，手势操作与舞台上的物理演示同步，形成「我操作、我体验、我理解」的深度参与感。车内还配备语音助手功能，用户可语音提问「座椅怎么调」「空调怎么开」，系统自动演示对应操作，将功能介绍变为用户主动探索。"
          }
        ]
      },
      {
        "type": "paragraph",
        "attrs": {
          "textAlign": null
        },
        "content": [
          {
            "type": "text",
            "text": "---"
          }
        ]
      },
      {
        "type": "heading",
        "attrs": {
          "textAlign": null,
          "level": 2
        },
        "content": [
          {
            "type": "text",
            "text": "第三章：活动整体结构与章节设计"
          }
        ]
      },
      {
        "type": "heading",
        "attrs": {
          "textAlign": null,
          "level": 3
        },
        "content": [
          {
            "type": "text",
            "text": "第一节：签到与情境导入——「入园」"
          }
        ]
      },
      {
        "type": "paragraph",
        "attrs": {
          "textAlign": null
        },
        "content": [
          {
            "type": "text",
            "marks": [
              {
                "type": "bold"
              }
            ],
            "text": "设计概念："
          },
          {
            "type": "text",
            "text": " 签到区不设传统签到台，而是以「入院」仪式替代。宾客抵达后，首先经过一道中式月洞门，门楣上方悬挂「一院」匾额（呼应主题），两侧对联为：「行车千里皆归路，庭院深处即吾家」。宾客领取一份「归家指南」——一张折叠式卡片，正面是庭院地图，背面是六色节点打卡页。"
          }
        ]
      },
      {
        "type": "paragraph",
        "attrs": {
          "textAlign": null
        },
        "content": [
          {
            "type": "text",
            "marks": [
              {
                "type": "bold"
              }
            ],
            "text": "空间氛围："
          },
          {
            "type": "text",
            "text": " 签到区背景采用水墨山水投影，配合古琴背景音乐，空间色调以「杜若白」为主（呼应车色「杜若白·源于古典香草的素白」），营造「未入庭院，心已归家」的氛围感。"
          }
        ]
      },
      {
        "type": "paragraph",
        "attrs": {
          "textAlign": null
        },
        "content": [
          {
            "type": "text",
            "marks": [
              {
                "type": "bold"
              }
            ],
            "text": "仪式感设计："
          },
          {
            "type": "text",
            "text": " 签到后，宾客从月洞门进入一条30米长廊，廊道两侧悬挂六组以「家」为主题的摄影作品（真实岚图车主家庭生活），每组照片下方配一句车主原话（如：「每次接女儿放学，她从车窗看到我就会笑」），光影设计模拟傍晚时分（暖黄色调），让宾客在步入主场地前已完成情感预热。"
          }
        ]
      },
      {
        "type": "paragraph",
        "attrs": {
          "textAlign": null
        },
        "content": [
          {
            "type": "text",
            "marks": [
              {
                "type": "bold"
              }
            ],
            "text": "时长规划："
          },
          {
            "type": "text",
            "text": " 签到+入园约15分钟，确保宾客在进入主场地前已完全进入「归家」心境。"
          }
        ]
      },
      {
        "type": "heading",
        "attrs": {
          "textAlign": null,
          "level": 3
        },
        "content": [
          {
            "type": "text",
            "text": "第二节：发布会主体——「开卷」"
          }
        ]
      },
      {
        "type": "paragraph",
        "attrs": {
          "textAlign": null
        },
        "content": [
          {
            "type": "text",
            "marks": [
              {
                "type": "bold"
              }
            ],
            "text": "开场仪式：「家书」启动（5分钟）"
          }
        ]
      },
      {
        "type": "paragraph",
        "attrs": {
          "textAlign": null
        },
        "content": [
          {
            "type": "text",
            "text": "不设领导致辞，直接播放「给家的信」视频。视频结束后，灯光渐亮，舞台中央缓缓升起一座微缩庭院模型（比例1:20），配乐转为悠扬笛声，主持人以「今日，我们不谈参数，只聊归途」为开场白，引出车型亮相。"
          }
        ]
      },
      {
        "type": "paragraph",
        "attrs": {
          "textAlign": null
        },
        "content": [
          {
            "type": "text",
            "marks": [
              {
                "type": "bold"
              }
            ],
            "text": "核心亮点发布（20分钟）"
          }
        ]
      },
      {
        "type": "paragraph",
        "attrs": {
          "textAlign": null
        },
        "content": [
          {
            "type": "text",
            "text": "采用「场景叙事」替代「产品讲解」，三个核心亮点分三个场景段落发布："
          }
        ]
      },
      {
        "type": "bulletList",
        "content": [
          {
            "type": "listItem",
            "content": [
              {
                "type": "paragraph",
                "attrs": {
                  "textAlign": null
                },
                "content": [
                  {
                    "type": "text",
                    "marks": [
                      {
                        "type": "bold"
                      }
                    ],
                    "text": "段落一（8分钟）：「庭院的空间」"
                  },
                  {
                    "type": "text",
                    "text": "——以「前院」空间为载体，展示6.1平米座舱带来的空间革命，配合「总统大三座」场景演示，讲述职场精英车内午休的真实需求如何被满足"
                  }
                ]
              }
            ]
          },
          {
            "type": "listItem",
            "content": [
              {
                "type": "paragraph",
                "attrs": {
                  "textAlign": null
                },
                "content": [
                  {
                    "type": "text",
                    "marks": [
                      {
                        "type": "bold"
                      }
                    ],
                    "text": "段落二（8分钟）：「归途的温度」"
                  },
                  {
                    "type": "text",
                    "text": "——以「中庭」空间为载体，展示六色车色的情感叙事，配合「豪华大四座」场景演示，讲述周末亲子露营如何从「计划」变为「享受」"
                  }
                ]
              }
            ]
          },
          {
            "type": "listItem",
            "content": [
              {
                "type": "paragraph",
                "attrs": {
                  "textAlign": null
                },
                "content": [
                  {
                    "type": "text",
                    "marks": [
                      {
                        "type": "bold"
                      }
                    ],
                    "text": "段落三（4分钟）：「回家的入口」"
                  },
                  {
                    "type": "text",
                    "text": "——以「后院」空间为载体，展示华为双联屏交互体验，配合「宽绰大五座」场景演示，讲述春节返乡场景中全家人的幸福时刻"
                  }
                ]
              }
            ]
          }
        ]
      },
      {
        "type": "paragraph",
        "attrs": {
          "textAlign": null
        },
        "content": [
          {
            "type": "text",
            "marks": [
              {
                "type": "bold"
              }
            ],
            "text": "车型亮相（3分钟）"
          }
        ]
      },
      {
        "type": "paragraph",
        "attrs": {
          "textAlign": null
        },
        "content": [
          {
            "type": "text",
            "text": "发布环节最后一个段落，庭院中央的微缩模型缓缓后移，真实车辆从后方卷轴造型的背景板后驶出，配合卷轴展开的视觉效果（「归山」意象），新车亮相瞬间全场灯光由暖黄转为「远山蓝」色调，寓意「归山而居」的主题升华。"
          }
        ]
      },
      {
        "type": "paragraph",
        "attrs": {
          "textAlign": null
        },
        "content": [
          {
            "type": "text",
            "marks": [
              {
                "type": "bold"
              }
            ],
            "text": "价格与权益发布（5分钟）"
          }
        ]
      },
      {
        "type": "paragraph",
        "attrs": {
          "textAlign": null
        },
        "content": [
          {
            "type": "text",
            "text": "车型亮相后，屏幕上显示「庭院级大五座SUV」的核心参数（以空间、温度、归途感为核心维度，非传统参数罗列），随即公布预售价及预售权益。权益设计紧扣「归家」主题：如「归家基金」（购车抵用）、首批车主「庭院入伙礼」（专属礼品）等。"
          }
        ]
      },
      {
        "type": "paragraph",
        "attrs": {
          "textAlign": null
        },
        "content": [
          {
            "type": "text",
            "marks": [
              {
                "type": "bold"
              }
            ],
            "text": "时长规划："
          },
          {
            "type": "text",
            "text": " 发布会主体约35分钟，整体节奏紧凑但情感饱满。"
          }
        ]
      },
      {
        "type": "heading",
        "attrs": {
          "textAlign": null,
          "level": 3
        },
        "content": [
          {
            "type": "text",
            "text": "第三节：沉浸式体验动线——「游园」"
          }
        ]
      },
      {
        "type": "paragraph",
        "attrs": {
          "textAlign": null
        },
        "content": [
          {
            "type": "text",
            "marks": [
              {
                "type": "bold"
              }
            ],
            "text": "设计概念："
          },
          {
            "type": "text",
            "text": " 发布会结束后，宾客正式进入庭院动线体验。动线全程约45分钟，设置5大节点，每个节点配置专属讲解员（着新中式服装，角色设定为「归家管家」），提供1对1或小团组（5-8人）的深度讲解体验。"
          }
        ]
      },
      {
        "type": "paragraph",
        "attrs": {
          "textAlign": null
        },
        "content": [
          {
            "type": "text",
            "marks": [
              {
                "type": "bold"
              }
            ],
            "text": "节点一：廊道——「望岳」"
          },
          {
            "type": "text",
            "text": "（8分钟）"
          }
        ]
      },
      {
        "type": "bulletList",
        "content": [
          {
            "type": "listItem",
            "content": [
              {
                "type": "paragraph",
                "attrs": {
                  "textAlign": null
                },
                "content": [
                  {
                    "type": "text",
                    "text": "核心体验：产品外观尺寸感知"
                  }
                ]
              }
            ]
          },
          {
            "type": "listItem",
            "content": [
              {
                "type": "paragraph",
                "attrs": {
                  "textAlign": null
                },
                "content": [
                  {
                    "type": "text",
                    "text": "空间设计：一条长40米的廊道，两侧悬挂岚图泰山X8的侧面剪影（从不同角度展示5200mm的车长），尽头是一个「框景」装置，透过框景看到车辆侧面全景，配以「山高人为峰」的文案"
                  }
                ]
              }
            ]
          },
          {
            "type": "listItem",
            "content": [
              {
                "type": "paragraph",
                "attrs": {
                  "textAlign": null
                },
                "content": [
                  {
                    "type": "text",
                    "text": "互动设计：廊道地面投影实时显示车辆尺寸数据（如「车长：5.2米」），用户行走时投影随脚步动态变化"
                  }
                ]
              }
            ]
          }
        ]
      },
      {
        "type": "paragraph",
        "attrs": {
          "textAlign": null
        },
        "content": [
          {
            "type": "text",
            "marks": [
              {
                "type": "bold"
              }
            ],
            "text": "节点二：前院——「问山」"
          },
          {
            "type": "text",
            "text": "（10分钟）"
          }
        ]
      },
      {
        "type": "bulletList",
        "content": [
          {
            "type": "listItem",
            "content": [
              {
                "type": "paragraph",
                "attrs": {
                  "textAlign": null
                },
                "content": [
                  {
                    "type": "text",
                    "text": "核心体验：6.1平米座舱空间感知"
                  }
                ]
              }
            ]
          },
          {
            "type": "listItem",
            "content": [
              {
                "type": "paragraph",
                "attrs": {
                  "textAlign": null
                },
                "content": [
                  {
                    "type": "text",
                    "text": "空间设计：复原前院场景，以中式矮墙、青石板地面、几株修竹围合出一个「室内庭院」，庭院中央摆放岚图泰山X8主驾座椅（放大版供多人体验），座椅旁设置「空间对照」装置——同时显示「6.1平米=几个车位」「6.1平米=多少个登机箱」"
                  }
                ]
              }
            ]
          },
          {
            "type": "listItem",
            "content": [
              {
                "type": "paragraph",
                "attrs": {
                  "textAlign": null
                },
                "content": [
                  {
                    "type": "text",
                    "text": "互动设计：「归家管家」邀请用户坐入座椅，体验座椅包裹感，同时打开车门让用户感受「庭院级」的空间感"
                  }
                ]
              }
            ]
          }
        ]
      },
      {
        "type": "paragraph",
        "attrs": {
          "textAlign": null
        },
        "content": [
          {
            "type": "text",
            "marks": [
              {
                "type": "bold"
              }
            ],
            "text": "节点三：中庭——「坐云」"
          },
          {
            "type": "text",
            "text": "（12分钟）"
          }
        ]
      },
      {
        "type": "bulletList",
        "content": [
          {
            "type": "listItem",
            "content": [
              {
                "type": "paragraph",
                "attrs": {
                  "textAlign": null
                },
                "content": [
                  {
                    "type": "text",
                    "text": "核心体验：三种座椅模式场景切换"
                  }
                ]
              }
            ]
          },
          {
            "type": "listItem",
            "content": [
              {
                "type": "paragraph",
                "attrs": {
                  "textAlign": null
                },
                "content": [
                  {
                    "type": "text",
                    "text": "空间设计：中庭设置「场景一键剧场」，配备真实可动的岚图泰山X8车内空间，用户可上车体验座椅模式切换。顶部星空灯带配合场景切换变色，前方投影幕布播放对应场景视频。"
                  }
                ]
              }
            ]
          },
          {
            "type": "listItem",
            "content": [
              {
                "type": "paragraph",
                "attrs": {
                  "textAlign": null
                },
                "content": [
                  {
                    "type": "text",
                    "text": "互动设计：用户可主动触发座椅切换，「归家管家」引导用户体验零重力座椅的调节功能，同时讲解「一键成床」等高频功能点"
                  }
                ]
              }
            ]
          }
        ]
      },
      {
        "type": "paragraph",
        "attrs": {
          "textAlign": null
        },
        "content": [
          {
            "type": "text",
            "marks": [
              {
                "type": "bold"
              }
            ],
            "text": "节点四：后院——「观星」"
          },
          {
            "type": "text",
            "text": "（10分钟）"
          }
        ]
      },
      {
        "type": "bulletList",
        "content": [
          {
            "type": "listItem",
            "content": [
              {
                "type": "paragraph",
                "attrs": {
                  "textAlign": null
                },
                "content": [
                  {
                    "type": "text",
                    "text": "核心体验：华为双联屏交互"
                  }
                ]
              }
            ]
          },
          {
            "type": "listItem",
            "content": [
              {
                "type": "paragraph",
                "attrs": {
                  "textAlign": null
                },
                "content": [
                  {
                    "type": "text",
                    "text": "空间设计：后院以「星空」为主题，顶部悬挂模拟星空的灯阵，用户可进入车内体验华为双联屏的交互功能。屏幕上预装「归家指南」应用，展示从家到岚图门店的路线、车内功能的动画演示等。"
                  }
                ]
              }
            ]
          },
          {
            "type": "listItem",
            "content": [
              {
                "type": "paragraph",
                "attrs": {
                  "textAlign": null
                },
                "content": [
                  {
                    "type": "text",
                    "text": "互动设计：「归家管家」邀请用户使用语音助手功能（语音唤醒：「小岚，我想回家」），体验智能座舱的交互流畅度，同时展示双联屏分屏功能（一屏导航、一屏娱乐）"
                  }
                ]
              }
            ]
          }
        ]
      },
      {
        "type": "paragraph",
        "attrs": {
          "textAlign": null
        },
        "content": [
          {
            "type": "text",
            "marks": [
              {
                "type": "bold"
              }
            ],
            "text": "节点五：揭幕区——「归山」"
          },
          {
            "type": "text",
            "text": "（5分钟）"
          }
        ]
      },
      {
        "type": "bulletList",
        "content": [
          {
            "type": "listItem",
            "content": [
              {
                "type": "paragraph",
                "attrs": {
                  "textAlign": null
                },
                "content": [
                  {
                    "type": "text",
                    "text": "核心体验：车型拍照打卡"
                  }
                ]
              }
            ]
          },
          {
            "type": "listItem",
            "content": [
              {
                "type": "paragraph",
                "attrs": {
                  "textAlign": null
                },
                "content": [
                  {
                    "type": "text",
                    "text": "空间设计：在车型揭幕后，揭幕区转化为拍照打卡区，背景是展开的「卷轴」（呼应亮相仪式），灯光以暖黄色为主，可拍摄与新车的合影。"
                  }
                ]
              }
            ]
          },
          {
            "type": "listItem",
            "content": [
              {
                "type": "paragraph",
                "attrs": {
                  "textAlign": null
                },
                "content": [
                  {
                    "type": "text",
                    "text": "互动设计：提供「新中式全家福」拍照服务，专业摄影师为用户拍摄家庭合影，可现场打印并装入相框（相框设计融入「卷轴」元素）"
                  }
                ]
              }
            ]
          }
        ]
      },
      {
        "type": "paragraph",
        "attrs": {
          "textAlign": null
        },
        "content": [
          {
            "type": "text",
            "marks": [
              {
                "type": "bold"
              }
            ],
            "text": "六色打卡联动设计："
          }
        ]
      },
      {
        "type": "paragraph",
        "attrs": {
          "textAlign": null
        },
        "content": [
          {
            "type": "text",
            "text": "五个节点之外，在庭院动线中穿插六个「色彩节点」，每个节点对应一款车色。用户在节点处扫描二维码可解锁「归家情绪时刻」音频/视频，完成全部六个节点打卡可获得「归山礼」一份（限量岚图泰山X8专属周边）。打卡数据实时同步至大屏幕，形成「全庭院的颜色汇聚」的动态可视化效果。"
          }
        ]
      },
      {
        "type": "heading",
        "attrs": {
          "textAlign": null,
          "level": 3
        },
        "content": [
          {
            "type": "text",
            "text": "第四节：收尾与离场——「归途」"
          }
        ]
      },
      {
        "type": "paragraph",
        "attrs": {
          "textAlign": null
        },
        "content": [
          {
            "type": "text",
            "marks": [
              {
                "type": "bold"
              }
            ],
            "text": "设计概念："
          },
          {
            "type": "text",
            "text": " 体验动线结束后，宾客离场时领取「归家礼」，同时填写「归家心愿卡」——写下对岚图泰山X8的一句话期待，投入中式灯笼造型的「心愿箱」中。心愿卡内容将在后续客户关怀中回访使用（购车顾问邀约素材）。"
          }
        ]
      },
      {
        "type": "paragraph",
        "attrs": {
          "textAlign": null
        },
        "content": [
          {
            "type": "text",
            "marks": [
              {
                "type": "bold"
              }
            ],
            "text": "归家礼设计："
          },
          {
            "type": "text",
            "text": " 每位宾客离场领取一个「归山礼盒」，内含："
          }
        ]
      },
      {
        "type": "bulletList",
        "content": [
          {
            "type": "listItem",
            "content": [
              {
                "type": "paragraph",
                "attrs": {
                  "textAlign": null
                },
                "content": [
                  {
                    "type": "text",
                    "text": "岚图泰山X8限量版「庭院」主题明信片（六色各一张）"
                  }
                ]
              }
            ]
          },
          {
            "type": "listItem",
            "content": [
              {
                "type": "paragraph",
                "attrs": {
                  "textAlign": null
                },
                "content": [
                  {
                    "type": "text",
                    "text": "「归家指南」手册（产品手册+活动回顾+六色故事手册）"
                  }
                ]
              }
            ]
          },
          {
            "type": "listItem",
            "content": [
              {
                "type": "paragraph",
                "attrs": {
                  "textAlign": null
                },
                "content": [
                  {
                    "type": "text",
                    "text": "小岚玩偶一只（品牌IP）"
                  }
                ]
              }
            ]
          },
          {
            "type": "listItem",
            "content": [
              {
                "type": "paragraph",
                "attrs": {
                  "textAlign": null
                },
                "content": [
                  {
                    "type": "text",
                    "text": "「归家基金」权益卡（预售价基础上额外抵用）"
                  }
                ]
              }
            ]
          }
        ]
      },
      {
        "type": "paragraph",
        "attrs": {
          "textAlign": null
        },
        "content": [
          {
            "type": "text",
            "marks": [
              {
                "type": "bold"
              }
            ],
            "text": "心愿卡运营："
          },
          {
            "type": "text",
            "text": " 现场设置心愿墙，收集的心愿卡在活动结束后整理归档，由销售顾问在一周内完成首批回访，问界M6的案例证明：活动后48小时内的高质量跟进可将预售转化率提升40%以上。"
          }
        ]
      },
      {
        "type": "paragraph",
        "attrs": {
          "textAlign": null
        },
        "content": [
          {
            "type": "text",
            "text": "---"
          }
        ]
      },
      {
        "type": "heading",
        "attrs": {
          "textAlign": null,
          "level": 2
        },
        "content": [
          {
            "type": "text",
            "text": "第四章：预算框架"
          }
        ]
      },
      {
        "type": "heading",
        "attrs": {
          "textAlign": null,
          "level": 3
        },
        "content": [
          {
            "type": "text",
            "text": "总预算：500-800万量级，本次方案以700万为基准展开"
          }
        ]
      },
      {
        "type": "heading",
        "attrs": {
          "textAlign": null,
          "level": 3
        },
        "content": [
          {
            "type": "text",
            "text": "预算分配"
          }
        ]
      },
      {
        "type": "paragraph",
        "attrs": {
          "textAlign": null
        },
        "content": [
          {
            "type": "text",
            "text": "预算项金额（万元）占比分配理由场地设计与搭建25035.7%庭院空间是核心体验载体，微型中式庭院搭建涉及大量定制材料（廊道、矮墙、卷轴、灯笼、竹影），及真实的车辆展示环境（含灯光系统、投影系统、音响系统），建议预算占总额35%以上以确保体验质感内容制作8011.4%「家书」视频制作（真实车主拍摄）、三组场景视频制作、六色情绪时刻音视频制作、华为双联屏界面设计，需高质量内容才能支撑情感体验演出与仪式405.7%古琴/笛子现场演出、「家书」演员出镜费用、灯光音效配合演出物料与礼品507.1%归山礼盒（含相框、明信片、玩偶）、六色节点打卡装置、归家心愿卡、「归家指南」手册印刷传播与媒体12017.1%预热期短视频投放、KOL/KOC邀约、现场直播、社交媒体话题运营、媒体大巴/酒店招待人员与执行608.6%活动执行团队、舞台导演、「归家管家」培训与薪酬、安保与后勤预留与应急507.1%预留不可预见费用，活动现场临时调整费用场地与餐饮507.1%场地租赁（城市级发布活动需核心城市大型场馆）、500-800人餐饮及接待**合计****700****100%**——"
          }
        ]
      },
      {
        "type": "heading",
        "attrs": {
          "textAlign": null,
          "level": 3
        },
        "content": [
          {
            "type": "text",
            "text": "预算弹性说明"
          }
        ]
      },
      {
        "type": "bulletList",
        "content": [
          {
            "type": "listItem",
            "content": [
              {
                "type": "paragraph",
                "attrs": {
                  "textAlign": null
                },
                "content": [
                  {
                    "type": "text",
                    "marks": [
                      {
                        "type": "bold"
                      }
                    ],
                    "text": "上浮至800万方案"
                  },
                  {
                    "type": "text",
                    "text": "：增加「场景一键剧场」的真车数量（从1台增加至2台），增加「家书」视频的拍摄周期（从3天增加至5天），增加KOL传播预算，扩大传播覆盖范围"
                  }
                ]
              }
            ]
          },
          {
            "type": "listItem",
            "content": [
              {
                "type": "paragraph",
                "attrs": {
                  "textAlign": null
                },
                "content": [
                  {
                    "type": "text",
                    "marks": [
                      {
                        "type": "bold"
                      }
                    ],
                    "text": "下调至500万方案"
                  },
                  {
                    "type": "text",
                    "text": "：缩减场地搭建规模（从完整庭院改为「半庭院」形式），减少场景视频制作量（从3组减少至1组），聚焦核心亮点执行"
                  }
                ]
              }
            ]
          }
        ]
      },
      {
        "type": "paragraph",
        "attrs": {
          "textAlign": null
        },
        "content": [
          {
            "type": "text",
            "text": "---"
          }
        ]
      },
      {
        "type": "heading",
        "attrs": {
          "textAlign": null,
          "level": 2
        },
        "content": [
          {
            "type": "text",
            "text": "第五章：执行节奏与关键里程碑"
          }
        ]
      },
      {
        "type": "heading",
        "attrs": {
          "textAlign": null,
          "level": 3
        },
        "content": [
          {
            "type": "text",
            "text": "预热期（活动前4周）"
          }
        ]
      },
      {
        "type": "paragraph",
        "attrs": {
          "textAlign": null
        },
        "content": [
          {
            "type": "text",
            "text": "时间节点里程碑任务产出D-28创意方案定稿完整活动方案及预算确认D-21内容制作启动「家书」脚本、场景视频脚本、六色情绪时刻脚本完成D-18场地勘察与确认活动场地签约完成D-14「家书」视频拍摄真实车主拍摄素材完成D-12舞台设计定稿舞台美术设计图确认D-10场景视频剪辑三组场景视频完成制作D-7华为双联屏界面设计车机界面设计稿确认D-5物料制作归山礼盒、归家心愿卡印刷完成D-3现场搭建启动庭院空间开始搭建D-1彩排与调试全流程彩排、灯光音效调试"
          }
        ]
      },
      {
        "type": "heading",
        "attrs": {
          "textAlign": null,
          "level": 3
        },
        "content": [
          {
            "type": "text",
            "text": "活动当天（D+0）"
          }
        ]
      },
      {
        "type": "paragraph",
        "attrs": {
          "textAlign": null
        },
        "content": [
          {
            "type": "text",
            "text": "时间节点里程碑任务产出T-2:00现场准备完成庭院空间布置就绪、车辆到位T-1:30彩排完成发布会流程彩排、场景切换测试T-1:00嘉宾入场签到、发放归家指南、入园引导T+0:00「家书」开场发布会正式开始T+0:35车型亮相岚图泰山X8正式揭幕T+0:40价格发布预售价及权益公布T+0:50游园动线开放宾客进入沉浸式体验T+1:35体验动线结束最后批次宾客体验完成T+1:50归山礼发放心愿卡填写、礼品发放T+2:00活动结束清场、媒体撤场"
          }
        ]
      },
      {
        "type": "heading",
        "attrs": {
          "textAlign": null,
          "level": 3
        },
        "content": [
          {
            "type": "text",
            "text": "收尾期（活动后2周）"
          }
        ]
      },
      {
        "type": "paragraph",
        "attrs": {
          "textAlign": null
        },
        "content": [
          {
            "type": "text",
            "text": "时间节点里程碑任务产出D+1传播内容发布官方素材发布、媒体稿件发布D+2客户回访启动销售顾问跟进心愿卡客户D+7活动复盘报告数据分析、用户反馈汇总D+14二次传播启动UGC内容整理、二次传播素材发布"
          }
        ]
      },
      {
        "type": "paragraph",
        "attrs": {
          "textAlign": null
        },
        "content": [
          {
            "type": "text",
            "text": "---"
          }
        ]
      },
      {
        "type": "heading",
        "attrs": {
          "textAlign": null,
          "level": 2
        },
        "content": [
          {
            "type": "text",
            "text": "第六章：核心KPI"
          }
        ]
      },
      {
        "type": "heading",
        "attrs": {
          "textAlign": null,
          "level": 3
        },
        "content": [
          {
            "type": "text",
            "text": "传播维度"
          }
        ]
      },
      {
        "type": "paragraph",
        "attrs": {
          "textAlign": null
        },
        "content": [
          {
            "type": "text",
            "text": "指标目标值设定理由话题阅读量5000万+参考问界M6的传播量级，岚图泰山X8需要建立足够的话题声量才能支撑「庭院级」的差异化定位传播短视频播放量2000万+预热期3条主视频+活动当天1条爆款视频的预期播放量，通过「家书」情感内容引发二次传播媒体自发报道50篇+活动结束后一周内媒体自发跟进报道的数量预期，需确保活动话题性足够强UGC内容数1000条+以「六色归山」打卡机制引导用户产出社交内容，形成自然传播"
          }
        ]
      },
      {
        "type": "heading",
        "attrs": {
          "textAlign": null,
          "level": 3
        },
        "content": [
          {
            "type": "text",
            "text": "销售转化维度"
          }
        ]
      },
      {
        "type": "paragraph",
        "attrs": {
          "textAlign": null
        },
        "content": [
          {
            "type": "text",
            "text": "指标目标值设定理由预售订单量5000+参考问界M6预售10万的数据，岚图泰山X8作为新车上市需要建立市场信心，首日5000订单是合理的基准线留资率85%+500-800人活动中，留资率85%以上意味着至少425组高意向客户现场转化率15%+活动当天现场下单或支付定金的比例线索转化周期48小时内参照问界M6案例，活动后48小时内的高质量跟进可将转化率提升40%，必须在该窗口内完成首批回访"
          }
        ]
      },
      {
        "type": "heading",
        "attrs": {
          "textAlign": null,
          "level": 3
        },
        "content": [
          {
            "type": "text",
            "text": "体验质量维度"
          }
        ]
      },
      {
        "type": "paragraph",
        "attrs": {
          "textAlign": null
        },
        "content": [
          {
            "type": "text",
            "text": "指标目标值设定理由宾客满意度90%+通过离场问卷收集，核心指标反映庭院体验的完成度亮点体验完成率95%+宾客完成全部5个体验节点的比例，反映动线设计的合理性六色打卡完成率60%+60%的宾客完成全部六个颜色节点打卡，说明打卡机制设计有效"
          }
        ]
      },
      {
        "type": "paragraph",
        "attrs": {
          "textAlign": null
        },
        "content": [
          {
            "type": "text",
            "text": "---"
          }
        ]
      },
      {
        "type": "heading",
        "attrs": {
          "textAlign": null,
          "level": 2
        },
        "content": [
          {
            "type": "text",
            "text": "第七章：风险应对"
          }
        ]
      },
      {
        "type": "heading",
        "attrs": {
          "textAlign": null,
          "level": 3
        },
        "content": [
          {
            "type": "text",
            "text": "风险一：产品亮点感知不足"
          }
        ]
      },
      {
        "type": "paragraph",
        "attrs": {
          "textAlign": null
        },
        "content": [
          {
            "type": "text",
            "marks": [
              {
                "type": "bold"
              }
            ],
            "text": "风险描述："
          },
          {
            "type": "text",
            "text": " 如果宾客在体验动线中对「庭院级」的核心卖点感知不足，可能导致活动沦为「拍照打卡」而非「产品种草」。"
          }
        ]
      },
      {
        "type": "paragraph",
        "attrs": {
          "textAlign": null
        },
        "content": [
          {
            "type": "text",
            "marks": [
              {
                "type": "bold"
              }
            ],
            "text": "应对措施："
          }
        ]
      },
      {
        "type": "bulletList",
        "content": [
          {
            "type": "listItem",
            "content": [
              {
                "type": "paragraph",
                "attrs": {
                  "textAlign": null
                },
                "content": [
                  {
                    "type": "text",
                    "text": "在每个体验节点设置「归家管家」，提供1对1讲解，确保核心卖点被主动传递"
                  }
                ]
              }
            ]
          },
          {
            "type": "listItem",
            "content": [
              {
                "type": "paragraph",
                "attrs": {
                  "textAlign": null
                },
                "content": [
                  {
                    "type": "text",
                    "text": "节点体验结束后，屏幕自动弹出「买点小结」，用一句话概括该节点的体验价值"
                  }
                ]
              }
            ]
          },
          {
            "type": "listItem",
            "content": [
              {
                "type": "paragraph",
                "attrs": {
                  "textAlign": null
                },
                "content": [
                  {
                    "type": "text",
                    "text": "游园动线结束后，设置「归家问答」互动装置（3道选择题），答对可获得额外礼品，通过问题设计让宾客主动复述产品卖点"
                  }
                ]
              }
            ]
          }
        ]
      },
      {
        "type": "heading",
        "attrs": {
          "textAlign": null,
          "level": 3
        },
        "content": [
          {
            "type": "text",
            "text": "风险二：场地搭建延误"
          }
        ]
      },
      {
        "type": "paragraph",
        "attrs": {
          "textAlign": null
        },
        "content": [
          {
            "type": "text",
            "marks": [
              {
                "type": "bold"
              }
            ],
            "text": "风险描述："
          },
          {
            "type": "text",
            "text": " 中式庭院搭建涉及大量定制材料，现场搭建周期紧张，可能出现时间不够的问题。"
          }
        ]
      },
      {
        "type": "paragraph",
        "attrs": {
          "textAlign": null
        },
        "content": [
          {
            "type": "text",
            "marks": [
              {
                "type": "bold"
              }
            ],
            "text": "应对措施："
          }
        ]
      },
      {
        "type": "bulletList",
        "content": [
          {
            "type": "listItem",
            "content": [
              {
                "type": "paragraph",
                "attrs": {
                  "textAlign": null
                },
                "content": [
                  {
                    "type": "text",
                    "text": "预留2天搭建时间（D-3至D-1），比常规活动多预留1天"
                  }
                ]
              }
            ]
          },
          {
            "type": "listItem",
            "content": [
              {
                "type": "paragraph",
                "attrs": {
                  "textAlign": null
                },
                "content": [
                  {
                    "type": "text",
                    "text": "核心材料（如卷轴、灯笼、矮墙）提前在工厂预制完成，现场仅组装"
                  }
                ]
              }
            ]
          },
          {
            "type": "listItem",
            "content": [
              {
                "type": "paragraph",
                "attrs": {
                  "textAlign": null
                },
                "content": [
                  {
                    "type": "text",
                    "text": "准备「简化版庭院」方案，如遇突发情况可在6小时内切换为半庭院形式"
                  }
                ]
              }
            ]
          }
        ]
      },
      {
        "type": "heading",
        "attrs": {
          "textAlign": null,
          "level": 3
        },
        "content": [
          {
            "type": "text",
            "text": "风险三：嘉宾体验动线拥堵"
          }
        ]
      },
      {
        "type": "paragraph",
        "attrs": {
          "textAlign": null
        },
        "content": [
          {
            "type": "text",
            "marks": [
              {
                "type": "bold"
              }
            ],
            "text": "风险描述："
          },
          {
            "type": "text",
            "text": " 500-800人同时进入体验动线，可能导致节点拥堵，降低体验质量。"
          }
        ]
      },
      {
        "type": "paragraph",
        "attrs": {
          "textAlign": null
        },
        "content": [
          {
            "type": "text",
            "marks": [
              {
                "type": "bold"
              }
            ],
            "text": "应对措施："
          }
        ]
      },
      {
        "type": "bulletList",
        "content": [
          {
            "type": "listItem",
            "content": [
              {
                "type": "paragraph",
                "attrs": {
                  "textAlign": null
                },
                "content": [
                  {
                    "type": "text",
                    "text": "分批次放行，每批50-60人，间隔10分钟"
                  }
                ]
              }
            ]
          },
          {
            "type": "listItem",
            "content": [
              {
                "type": "paragraph",
                "attrs": {
                  "textAlign": null
                },
                "content": [
                  {
                    "type": "text",
                    "text": "节点设置「预约制」，宾客可在签到时领取预约时段卡片"
                  }
                ]
              }
            ]
          },
          {
            "type": "listItem",
            "content": [
              {
                "type": "paragraph",
                "attrs": {
                  "textAlign": null
                },
                "content": [
                  {
                    "type": "text",
                    "text": "备有「快速通道」，对于时间紧张的VIP宾客可跳过部分节点，直接进入核心节点"
                  }
                ]
              }
            ]
          }
        ]
      },
      {
        "type": "heading",
        "attrs": {
          "textAlign": null,
          "level": 3
        },
        "content": [
          {
            "type": "text",
            "text": "风险四：传播素材质量不稳定"
          }
        ]
      },
      {
        "type": "paragraph",
        "attrs": {
          "textAlign": null
        },
        "content": [
          {
            "type": "text",
            "marks": [
              {
                "type": "bold"
              }
            ],
            "text": "风险描述："
          },
          {
            "type": "text",
            "text": " 「家书」视频和场景视频是传播的核心素材，如质量不达标，将直接影响传播效果。"
          }
        ]
      },
      {
        "type": "paragraph",
        "attrs": {
          "textAlign": null
        },
        "content": [
          {
            "type": "text",
            "marks": [
              {
                "type": "bold"
              }
            ],
            "text": "应对措施："
          }
        ]
      },
      {
        "type": "bulletList",
        "content": [
          {
            "type": "listItem",
            "content": [
              {
                "type": "paragraph",
                "attrs": {
                  "textAlign": null
                },
                "content": [
                  {
                    "type": "text",
                    "text": "选择有汽车发布会内容制作经验的团队，避免试错成本"
                  }
                ]
              }
            ]
          },
          {
            "type": "listItem",
            "content": [
              {
                "type": "paragraph",
                "attrs": {
                  "textAlign": null
                },
                "content": [
                  {
                    "type": "text",
                    "text": "脚本阶段引入客户方评审，确保情感调性与品牌调性一致"
                  }
                ]
              }
            ]
          },
          {
            "type": "listItem",
            "content": [
              {
                "type": "paragraph",
                "attrs": {
                  "textAlign": null
                },
                "content": [
                  {
                    "type": "text",
                    "text": "设置3轮审核节点（脚本审核、粗剪审核、成片审核），层层把关"
                  }
                ]
              }
            ]
          }
        ]
      },
      {
        "type": "heading",
        "attrs": {
          "textAlign": null,
          "level": 3
        },
        "content": [
          {
            "type": "text",
            "text": "风险五：竞品动态影响"
          }
        ]
      },
      {
        "type": "paragraph",
        "attrs": {
          "textAlign": null
        },
        "content": [
          {
            "type": "text",
            "marks": [
              {
                "type": "bold"
              }
            ],
            "text": "风险描述："
          },
          {
            "type": "text",
            "text": " 活动期间竞品可能发布新车或调整价格，冲击岚图泰山X8的传播声量。"
          }
        ]
      },
      {
        "type": "paragraph",
        "attrs": {
          "textAlign": null
        },
        "content": [
          {
            "type": "text",
            "marks": [
              {
                "type": "bold"
              }
            ],
            "text": "应对措施："
          }
        ]
      },
      {
        "type": "bulletList",
        "content": [
          {
            "type": "listItem",
            "content": [
              {
                "type": "paragraph",
                "attrs": {
                  "textAlign": null
                },
                "content": [
                  {
                    "type": "text",
                    "text": "在活动前2天完成所有传播素材的预排期，确活动当天内容同步发出"
                  }
                ]
              }
            ]
          },
          {
            "type": "listItem",
            "content": [
              {
                "type": "paragraph",
                "attrs": {
                  "textAlign": null
                },
                "content": [
                  {
                    "type": "text",
                    "text": "设置「竞品应急响应」机制，如遇竞品动态，可24小时内产出应对物料"
                  }
                ]
              }
            ]
          },
          {
            "type": "listItem",
            "content": [
              {
                "type": "paragraph",
                "attrs": {
                  "textAlign": null
                },
                "content": [
                  {
                    "type": "text",
                    "text": "传播内容设计为「产品体验」导向而非「参数对比」导向，降低被直接对比的风险"
                  }
                ]
              }
            ]
          }
        ]
      },
      {
        "type": "paragraph",
        "attrs": {
          "textAlign": null
        },
        "content": [
          {
            "type": "text",
            "text": "---"
          }
        ]
      },
      {
        "type": "heading",
        "attrs": {
          "textAlign": null,
          "level": 2
        },
        "content": [
          {
            "type": "text",
            "text": "第八章：现场效果建议"
          }
        ]
      },
      {
        "type": "heading",
        "attrs": {
          "textAlign": null,
          "level": 3
        },
        "content": [
          {
            "type": "text",
            "text": "视觉建议"
          }
        ]
      },
      {
        "type": "paragraph",
        "attrs": {
          "textAlign": null
        },
        "content": [
          {
            "type": "text",
            "marks": [
              {
                "type": "bold"
              }
            ],
            "text": "整体视觉基调："
          },
          {
            "type": "text",
            "text": " 中式优雅×现代空间的克制美学——以「留白」与「围合」营造庭院式的包裹感，色彩语言从车色诗意中延伸，整体像一部有质感的家庭生活纪录片。避免传统汽车发布会常见的「科技感爆棚」「蓝光炫目」，用「暖色调」「自然材质」「手工感」传递「归家」的温度。"
          }
        ]
      },
      {
        "type": "paragraph",
        "attrs": {
          "textAlign": null
        },
        "content": [
          {
            "type": "text",
            "marks": [
              {
                "type": "bold"
              }
            ],
            "text": "色彩系统："
          }
        ]
      },
      {
        "type": "bulletList",
        "content": [
          {
            "type": "listItem",
            "content": [
              {
                "type": "paragraph",
                "attrs": {
                  "textAlign": null
                },
                "content": [
                  {
                    "type": "text",
                    "text": "主色调：杜若白（素白）、玄英黑（深夜黑）形成「明暗对比」"
                  }
                ]
              }
            ]
          },
          {
            "type": "listItem",
            "content": [
              {
                "type": "paragraph",
                "attrs": {
                  "textAlign": null
                },
                "content": [
                  {
                    "type": "text",
                    "text": "点缀色：碧玺红（暖光）、远山蓝（冷光）形成「冷暖对比」"
                  }
                ]
              }
            ]
          },
          {
            "type": "listItem",
            "content": [
              {
                "type": "paragraph",
                "attrs": {
                  "textAlign": null
                },
                "content": [
                  {
                    "type": "text",
                    "text": "中性色：宸星灰（中性灰）、星光银（金属银）作为过渡色"
                  }
                ]
              }
            ]
          },
          {
            "type": "listItem",
            "content": [
              {
                "type": "paragraph",
                "attrs": {
                  "textAlign": null
                },
                "content": [
                  {
                    "type": "text",
                    "text": "整体氛围：以傍晚/黄昏时分的「归家光线」为核心视觉基调"
                  }
                ]
              }
            ]
          }
        ]
      },
      {
        "type": "paragraph",
        "attrs": {
          "textAlign": null
        },
        "content": [
          {
            "type": "text",
            "marks": [
              {
                "type": "bold"
              }
            ],
            "text": "核心装置建议："
          }
        ]
      },
      {
        "type": "bulletList",
        "content": [
          {
            "type": "listItem",
            "content": [
              {
                "type": "paragraph",
                "attrs": {
                  "textAlign": null
                },
                "content": [
                  {
                    "type": "text",
                    "text": "入口月洞门：高度4米，宽度3米，材质为哑光金属+木质纹路贴面"
                  }
                ]
              }
            ]
          },
          {
            "type": "listItem",
            "content": [
              {
                "type": "paragraph",
                "attrs": {
                  "textAlign": null
                },
                "content": [
                  {
                    "type": "text",
                    "text": "廊道灯笼：直径30cm的纸灯笼，内置暖色灯带，间隔2米悬挂"
                  }
                ]
              }
            ]
          },
          {
            "type": "listItem",
            "content": [
              {
                "type": "paragraph",
                "attrs": {
                  "textAlign": null
                },
                "content": [
                  {
                    "type": "text",
                    "text": "场景剧场投影幕：120寸激光投影幕，融合于庭院场景中不突兀"
                  }
                ]
              }
            ]
          },
          {
            "type": "listItem",
            "content": [
              {
                "type": "paragraph",
                "attrs": {
                  "textAlign": null
                },
                "content": [
                  {
                    "type": "text",
                    "text": "卷轴揭幕背景：宽15米、高6米，卷轴展开动画配合车辆驶出"
                  }
                ]
              }
            ]
          }
        ]
      },
      {
        "type": "heading",
        "attrs": {
          "textAlign": null,
          "level": 3
        },
        "content": [
          {
            "type": "text",
            "text": "音乐建议"
          }
        ]
      },
      {
        "type": "paragraph",
        "attrs": {
          "textAlign": null
        },
        "content": [
          {
            "type": "text",
            "marks": [
              {
                "type": "bold"
              }
            ],
            "text": "空间背景音乐："
          },
          {
            "type": "text",
            "text": " 全程以「中式古典+现代轻音乐」融合风格为主，避免过于激昂的电子音乐。推荐元素：古琴、笛子、钢琴、弦乐四重奏。"
          }
        ]
      },
      {
        "type": "bulletList",
        "content": [
          {
            "type": "listItem",
            "content": [
              {
                "type": "paragraph",
                "attrs": {
                  "textAlign": null
                },
                "content": [
                  {
                    "type": "text",
                    "text": "签到区：古琴独奏，轻柔悠远"
                  }
                ]
              }
            ]
          },
          {
            "type": "listItem",
            "content": [
              {
                "type": "paragraph",
                "attrs": {
                  "textAlign": null
                },
                "content": [
                  {
                    "type": "text",
                    "text": "发布会：「家书」视频配乐选用钢琴+弦乐，情感饱满；车型亮相配乐选用笛子+鼓点，庄重而不失灵动"
                  }
                ]
              }
            ]
          },
          {
            "type": "listItem",
            "content": [
              {
                "type": "paragraph",
                "attrs": {
                  "textAlign": null
                },
                "content": [
                  {
                    "type": "text",
                    "text": "体验动线：每节点背景音乐与该节点主题呼应（如「坐云」节点使用风声+虫鸣+轻爵士）"
                  }
                ]
              }
            ]
          }
        ]
      },
      {
        "type": "heading",
        "attrs": {
          "textAlign": null,
          "level": 3
        },
        "content": [
          {
            "type": "text",
            "text": "气味建议"
          }
        ]
      },
      {
        "type": "paragraph",
        "attrs": {
          "textAlign": null
        },
        "content": [
          {
            "type": "text",
            "text": "引入「嗅觉营销」概念，在不同节点释放不同香味："
          }
        ]
      },
      {
        "type": "bulletList",
        "content": [
          {
            "type": "listItem",
            "content": [
              {
                "type": "paragraph",
                "attrs": {
                  "textAlign": null
                },
                "content": [
                  {
                    "type": "text",
                    "text": "签到区：杜若白香型（类似香草的清新气息，呼应车色「杜若白·源于古典香草的素白」）"
                  }
                ]
              }
            ]
          },
          {
            "type": "listItem",
            "content": [
              {
                "type": "paragraph",
                "attrs": {
                  "textAlign": null
                },
                "content": [
                  {
                    "type": "text",
                    "text": "「问山」节点：木质香型（雪松/檀木，传递「归家」的沉稳感）"
                  }
                ]
              }
            ]
          },
          {
            "type": "listItem",
            "content": [
              {
                "type": "paragraph",
                "attrs": {
                  "textAlign": null
                },
                "content": [
                  {
                    "type": "text",
                    "text": "「观星」节点：星空香型（薰衣草+薄荷，帮助用户放松体验智能座舱）"
                  }
                ]
              }
            ]
          }
        ]
      },
      {
        "type": "paragraph",
        "attrs": {
          "textAlign": null
        },
        "content": [
          {
            "type": "text",
            "text": "---"
          }
        ]
      },
      {
        "type": "heading",
        "attrs": {
          "textAlign": null,
          "level": 2
        },
        "content": [
          {
            "type": "text",
            "text": "第九章：创意延续建议"
          }
        ]
      },
      {
        "type": "heading",
        "attrs": {
          "textAlign": null,
          "level": 3
        },
        "content": [
          {
            "type": "text",
            "text": "从活动到品牌"
          }
        ]
      },
      {
        "type": "paragraph",
        "attrs": {
          "textAlign": null
        },
        "content": [
          {
            "type": "text",
            "text": "「一院·一程·一归家」的核心创意不应止步于一场活动，而应成为岚图泰山X8的长期品牌叙事资产："
          }
        ]
      },
      {
        "type": "paragraph",
        "attrs": {
          "textAlign": null
        },
        "content": [
          {
            "type": "text",
            "text": "1. "
          },
          {
            "type": "text",
            "marks": [
              {
                "type": "bold"
              }
            ],
            "text": "产品手册设计："
          },
          {
            "type": "text",
            "text": " 将产品手册设计为「归家指南」形式，以「六色归山」为章节结构，每款车色对应一个「归家的情绪时刻」"
          }
        ]
      },
      {
        "type": "paragraph",
        "attrs": {
          "textAlign": null
        },
        "content": [
          {
            "type": "text",
            "text": "2. "
          },
          {
            "type": "text",
            "marks": [
              {
                "type": "bold"
              }
            ],
            "text": "终端展厅升级："
          },
          {
            "type": "text",
            "text": " 将岚图展厅设计融入庭院元素，设置「庭院式体验区」，用户可在模拟庭院场景中体验车型"
          }
        ]
      },
      {
        "type": "paragraph",
        "attrs": {
          "textAlign": null
        },
        "content": [
          {
            "type": "text",
            "text": "3. "
          },
          {
            "type": "text",
            "marks": [
              {
                "type": "bold"
              }
            ],
            "text": "用户社区运营："
          },
          {
            "type": "text",
            "text": " 建立「归家人」用户社区，定期组织「归家主题」用户活动（如「归家摄影展」「归家故事分享」）"
          }
        ]
      },
      {
        "type": "paragraph",
        "attrs": {
          "textAlign": null
        },
        "content": [
          {
            "type": "text",
            "text": "4. "
          },
          {
            "type": "text",
            "marks": [
              {
                "type": "bold"
              }
            ],
            "text": "年度传播主题："
          },
          {
            "type": "text",
            "text": " 将「庭院级大五座SUV」作为岚图泰山X8的年度传播主题，持续强化产品与「家·出行·幸福」的情感连接"
          }
        ]
      },
      {
        "type": "paragraph",
        "attrs": {
          "textAlign": null
        },
        "content": [
          {
            "type": "text",
            "text": "---"
          }
        ]
      }
    ]
  },
  "createdAt": "2026-04-21T15:26:53.187Z",
  "updatedAt": "2026-04-22T17:25:34.301Z"
}